setup.py
rst_archiver/__init__.py
rst_archiver/cmdline.py
rst_archiver/main.py
rst_archiver.egg-info/PKG-INFO
rst_archiver.egg-info/SOURCES.txt
rst_archiver.egg-info/dependency_links.txt
rst_archiver.egg-info/entry_points.txt
rst_archiver.egg-info/pbr.json
rst_archiver.egg-info/requires.txt
rst_archiver.egg-info/top_level.txt