Metadata-Version: 1.1
Name: rst-archiver
Version: 0.1.1
Summary: Add files to your RST notes more easily.
Home-page: https://github.com/coddingtonbear/rst-archiver
Author: Adam Coddington
Author-email: me@adamcoddington.net
License: UNKNOWN
Platform: UNKNOWN
Classifier: License :: OSI Approved :: MIT License
Classifier: Operating System :: OS Independent
